<?xml version="1.0" encoding="utf-8" ?>
<dwsync>
<file name="reset.css" local="129901257532200000" remote="0" testing="129901257530000000" />
<file name="screen.css" local="129909178298720073" remote="0" testing="129909178290000000" />
<file name="Chunkfive-webfont.eot" local="129901310970470000" remote="0" testing="129901310970000000" />
<file name="Chunkfive-webfont.svg" local="129901310973720000" remote="0" testing="129901310970000000" />
<file name="Chunkfive-webfont.ttf" local="129901310974300000" remote="0" testing="129901310970000000" />
<file name="Chunkfive-webfont.woff" local="129901310975430000" remote="0" testing="129901310970000000" />
<file name="credentials to server.txt 2.gpg" local="129896867939234589" remote="0" testing="129896867930000000" />
<file name="ie6.css" local="129909175056300073" remote="0" testing="129909175050000000" />
<file name="ie7.css" local="129909154570260073" remote="0" testing="129909154570000000" />
<file name="ie8.css" local="129909154381280073" remote="0" testing="129909154380000000" />
</dwsync>